[
  {"id": 1, "category": "제품", "response_text": "배송이 빠르고 포장이 꼼꼼했습니다. 매우 만족합니다!", "satisfaction_score": 5, "timestamp": "2024-01-15 09:30:00"},
  {"id": 2, "category": "서비스", "response_text": "고객센터 응대가 친절했어요. 문의 해결이 빨랐습니다.", "satisfaction_score": 5, "timestamp": "2024-01-15 10:15:00"},
  {"id": 3, "category": "제품", "response_text": "품질이 기대 이하였습니다. 사진과 달라요.", "satisfaction_score": 2, "timestamp": "2024-01-15 11:00:00"},
  {"id": 4, "category": "배송", "response_text": "배송 지연이 있었습니다. 예상보다 3일 늦게 도착.", "satisfaction_score": 2, "timestamp": "2024-01-15 11:45:00"},
  {"id": 5, "category": "서비스", "response_text": "교환 절차가 복잡했습니다. 개선이 필요해요.", "satisfaction_score": 3, "timestamp": "2024-01-15 13:00:00"},
  {"id": 6, "category": "제품", "response_text": "가격 대비 품질이 좋습니다. 재구매 의향 있어요.", "satisfaction_score": 4, "timestamp": "2024-01-15 14:30:00"},
  {"id": 7, "category": "제품", "response_text": "색상이 예쁘고 사이즈도 딱 맞아요!", "satisfaction_score": 5, "timestamp": "2024-01-15 15:00:00"},
  {"id": 8, "category": "배송", "response_text": "새벽배송 너무 좋아요. 신선하게 받았습니다.", "satisfaction_score": 5, "timestamp": "2024-01-15 16:00:00"},
  {"id": 9, "category": "서비스", "response_text": "반품 처리가 신속했습니다. 감사합니다.", "satisfaction_score": 4, "timestamp": "2024-01-15 17:00:00"},
  {"id": 10, "category": "제품", "response_text": "설명서가 없어서 사용법을 몰랐어요.", "satisfaction_score": 3, "timestamp": "2024-01-16 09:00:00"},
  {"id": 11, "category": "배송", "response_text": "택배 기사님이 친절하셨습니다.", "satisfaction_score": 5, "timestamp": "2024-01-16 09:30:00"},
  {"id": 12, "category": "서비스", "response_text": "앱 사용이 불편합니다. UI 개선 바랍니다.", "satisfaction_score": 2, "timestamp": "2024-01-16 10:00:00"},
  {"id": 13, "category": "제품", "response_text": "품질 최고입니다. 주변에 추천하고 싶어요.", "satisfaction_score": 5, "timestamp": "2024-01-16 10:30:00"},
  {"id": 14, "category": "제품", "response_text": "가격이 조금 비싼 것 같아요.", "satisfaction_score": 3, "timestamp": "2024-01-16 11:00:00"},
  {"id": 15, "category": "배송", "response_text": "포장이 훼손되어 왔습니다. 아쉬워요.", "satisfaction_score": 2, "timestamp": "2024-01-16 11:30:00"},
  {"id": 16, "category": "서비스", "response_text": "문의 답변이 늦었습니다. 3일이나 걸렸어요.", "satisfaction_score": 2, "timestamp": "2024-01-16 12:00:00"},
  {"id": 17, "category": "제품", "response_text": "디자인이 세련되고 고급스러워요.", "satisfaction_score": 5, "timestamp": "2024-01-16 13:00:00"},
  {"id": 18, "category": "제품", "response_text": "소재가 좋고 마감이 깔끔합니다.", "satisfaction_score": 4, "timestamp": "2024-01-16 13:30:00"},
  {"id": 19, "category": "배송", "response_text": "정확한 시간에 배송됐습니다. 완벽해요!", "satisfaction_score": 5, "timestamp": "2024-01-16 14:00:00"},
  {"id": 20, "category": "서비스", "response_text": "적립금 사용이 편리했습니다.", "satisfaction_score": 4, "timestamp": "2024-01-16 14:30:00"},
  {"id": 21, "category": "제품", "response_text": "냄새가 좀 나요. 환기 필요합니다.", "satisfaction_score": 3, "timestamp": "2024-01-17 09:00:00"},
  {"id": 22, "category": "제품", "response_text": "튼튼하고 오래 쓸 것 같아요.", "satisfaction_score": 4, "timestamp": "2024-01-17 09:30:00"},
  {"id": 23, "category": "배송", "response_text": "배송 추적이 잘 됩니다. 편리해요.", "satisfaction_score": 4, "timestamp": "2024-01-17 10:00:00"},
  {"id": 24, "category": "서비스", "response_text": "회원 혜택이 좋아요. 할인 많이 받았습니다.", "satisfaction_score": 5, "timestamp": "2024-01-17 10:30:00"},
  {"id": 25, "category": "제품", "response_text": "사용해보니 정말 편리합니다. 추천!", "satisfaction_score": 5, "timestamp": "2024-01-17 11:00:00"},
  {"id": 26, "category": "배송", "response_text": "명절에도 빠른 배송 감사합니다.", "satisfaction_score": 5, "timestamp": "2024-01-17 11:30:00"},
  {"id": 27, "category": "서비스", "response_text": "챗봇이 답답해요. 상담사 연결이 어려웠습니다.", "satisfaction_score": 2, "timestamp": "2024-01-17 12:00:00"},
  {"id": 28, "category": "제품", "response_text": "크기가 생각보다 작았어요.", "satisfaction_score": 3, "timestamp": "2024-01-17 13:00:00"},
  {"id": 29, "category": "제품", "response_text": "선물용으로 샀는데 포장이 예뻐요.", "satisfaction_score": 4, "timestamp": "2024-01-17 13:30:00"},
  {"id": 30, "category": "배송", "response_text": "부분 배송이 되어서 불편했어요.", "satisfaction_score": 3, "timestamp": "2024-01-17 14:00:00"},
  {"id": 31, "category": "서비스", "response_text": "이벤트 참여가 쉬웠습니다. 경품 당첨!", "satisfaction_score": 5, "timestamp": "2024-01-18 09:00:00"},
  {"id": 32, "category": "제품", "response_text": "AS가 잘 되어서 만족합니다.", "satisfaction_score": 4, "timestamp": "2024-01-18 09:30:00"},
  {"id": 33, "category": "제품", "response_text": "가성비 최고의 제품입니다.", "satisfaction_score": 5, "timestamp": "2024-01-18 10:00:00"},
  {"id": 34, "category": "배송", "response_text": "안전하게 잘 도착했습니다.", "satisfaction_score": 4, "timestamp": "2024-01-18 10:30:00"},
  {"id": 35, "category": "서비스", "response_text": "결제 오류가 있었는데 빠르게 해결됐어요.", "satisfaction_score": 4, "timestamp": "2024-01-18 11:00:00"},
  {"id": 36, "category": "제품", "response_text": "색상이 화면과 달라서 실망했어요.", "satisfaction_score": 2, "timestamp": "2024-01-18 11:30:00"},
  {"id": 37, "category": "제품", "response_text": "기능이 다양해서 좋습니다.", "satisfaction_score": 4, "timestamp": "2024-01-18 12:00:00"},
  {"id": 38, "category": "배송", "response_text": "우체국 택배라서 조금 느렸어요.", "satisfaction_score": 3, "timestamp": "2024-01-18 13:00:00"},
  {"id": 39, "category": "서비스", "response_text": "포인트 적립률이 높아서 좋아요.", "satisfaction_score": 4, "timestamp": "2024-01-18 13:30:00"},
  {"id": 40, "category": "제품", "response_text": "내구성이 걱정됩니다. 조금 약해 보여요.", "satisfaction_score": 3, "timestamp": "2024-01-18 14:00:00"},
  {"id": 41, "category": "배송", "response_text": "배송비가 아까워요. 무료배송 기준 낮춰주세요.", "satisfaction_score": 3, "timestamp": "2024-01-19 09:00:00"},
  {"id": 42, "category": "서비스", "response_text": "리뷰 작성하면 적립금 주는 게 좋아요.", "satisfaction_score": 4, "timestamp": "2024-01-19 09:30:00"},
  {"id": 43, "category": "제품", "response_text": "설치가 간편했습니다. 30분이면 끝!", "satisfaction_score": 5, "timestamp": "2024-01-19 10:00:00"},
  {"id": 44, "category": "제품", "response_text": "아이들이 좋아합니다. 재구매할게요.", "satisfaction_score": 5, "timestamp": "2024-01-19 10:30:00"},
  {"id": 45, "category": "배송", "response_text": "토요일에도 배송되어서 좋았어요.", "satisfaction_score": 4, "timestamp": "2024-01-19 11:00:00"},
  {"id": 46, "category": "서비스", "response_text": "멤버십 혜택이 다양합니다.", "satisfaction_score": 4, "timestamp": "2024-01-19 11:30:00"},
  {"id": 47, "category": "제품", "response_text": "전작보다 업그레이드된 느낌이에요.", "satisfaction_score": 4, "timestamp": "2024-01-19 12:00:00"},
  {"id": 48, "category": "배송", "response_text": "경비실에 맡겨주셔서 편했습니다.", "satisfaction_score": 4, "timestamp": "2024-01-19 13:00:00"},
  {"id": 49, "category": "서비스", "response_text": "쿠폰 사용이 복잡했어요. 중복 적용 안 됨.", "satisfaction_score": 2, "timestamp": "2024-01-19 13:30:00"},
  {"id": 50, "category": "제품", "response_text": "가격 인상이 있었네요. 아쉽습니다.", "satisfaction_score": 3, "timestamp": "2024-01-19 14:00:00"}
]





